setup.cfg
setup.py
easyapiio/File.py
easyapiio/Object.py
easyapiio/Random.py
easyapiio/__init__.py
easyapiio.egg-info/PKG-INFO
easyapiio.egg-info/SOURCES.txt
easyapiio.egg-info/dependency_links.txt
easyapiio.egg-info/not-zip-safe
easyapiio.egg-info/top_level.txt