Metadata-Version: 1.0
Name: easyapiio
Version: 0.1.31
Summary: A library to simplify the use of EasyAPI.io.
Home-page: https://github.com/easyapiio/easyapi-python-sdk
Author: keithweaver
Author-email: me@keithweaver.ca
License: MIT License
Platform: UNKNOWN
